speed_analyzer/__init__.py
speed_analyzer/nsi_calculator.py
speed_analyzer/analysis_modules/__init__.py
speed_analyzer/analysis_modules/bids_converter.py
speed_analyzer/analysis_modules/classify_cli.py
speed_analyzer/analysis_modules/device_converters.py
speed_analyzer/analysis_modules/dicom_converter.py
speed_analyzer/analysis_modules/realtime_analyzer.py
speed_analyzer/analysis_modules/speed_script_events.py
speed_analyzer/analysis_modules/video_generator.py
speed_analyzer/analysis_modules/yolo_analyzer.py
speed_analyzer-5.3.8.5.dist-info/licenses/LICENSE
speed_analyzer-5.3.8.5.dist-info/METADATA
speed_analyzer-5.3.8.5.dist-info/WHEEL
speed_analyzer-5.3.8.5.dist-info/top_level.txt
speed_analyzer-5.3.8.5.dist-info/RECORD
