Metadata-Version: 2.4
Name: speed-analyzer
Version: 5.3.8.5
Summary: A package for processing and extracting eye-tracking data.
Home-page: https://github.com/danielelozzi/SPEED
Author: Dr. Daniele Lozzi, LabSCoC
Project-URL: Homepage, https://github.com/danielelozzi/SPEED
Project-URL: Source, https://github.com/danielelozzi/SPEED
Project-URL: Bug Tracker, https://github.com/danielelozzi/SPEED/issues
Classifier: Programming Language :: Python :: 3
Classifier: License :: OSI Approved :: MIT License
Classifier: Operating System :: OS Independent
Requires-Python: >=3.10
License-File: LICENSE
Requires-Dist: pandas
Requires-Dist: numpy
Requires-Dist: matplotlib
Requires-Dist: opencv-python
Requires-Dist: scipy
Requires-Dist: tqdm
Requires-Dist: moviepy
Requires-Dist: ultralytics
Requires-Dist: Pillow
Requires-Dist: pupil-labs-realtime-api
Requires-Dist: pylsl
Dynamic: author
Dynamic: classifier
Dynamic: description
Dynamic: description-content-type
Dynamic: home-page
Dynamic: license-file
Dynamic: project-url
Dynamic: requires-dist
Dynamic: requires-python
Dynamic: summary
